hydrogr-1.2.2.dist-info/METADATA
hydrogr-1.2.2.dist-info/WHEEL
hydrogr-1.2.2.dist-info/licenses/LICENSE.txt
hydrogr/__init__.py
hydrogr/_hydrogr.cpython-311-aarch64-linux-gnu.so
hydrogr/gr1a.py
hydrogr/gr2m.py
hydrogr/gr4h.py
hydrogr/gr4j.py
hydrogr/gr5j.py
hydrogr/gr6j.py
hydrogr/input_data.py
hydrogr/model_interface.py
hydrogr-1.2.2.dist-info/RECORD
