Metadata-Version: 2.4
Name: hydrogr
Version: 1.2.2
Classifier: Programming Language :: Rust
Classifier: Programming Language :: Python :: Implementation :: CPython
Classifier: Programming Language :: Python :: Implementation :: PyPy
Requires-Dist: numpy>2.2.0
Requires-Dist: pandas>=2.2.0
License-File: LICENSE.txt
Summary: Hydrogr is a Python package that implement GR hydrological models in Rust
Author-email: SimonDelmas <delmas.simon@gmail.com>
Requires-Python: >=3.10
Project-URL: homepage, https://github.com/SimonDelmas/hydrogr
